setup.cfg
setup.py
django_kway.egg-info/PKG-INFO
django_kway.egg-info/SOURCES.txt
django_kway.egg-info/dependency_links.txt
django_kway.egg-info/top_level.txt
kway/__init__.py
kway/admin.py
kway/cache.py
kway/localization.py
kway/models.py
kway/settings.py
kway/translation.py
kway/utils.py
kway/version.py
kway/migrations/0001_initial.py
kway/migrations/__init__.py
kway/templatetags/__init__.py
kway/templatetags/kway_tags.py