Metadata-Version: 1.1
Name: django-kway
Version: 0.1.9
Summary: django-kway is an alternative to django gettext catalog with admin integration.
Home-page: https://github.com/fabiocaccamo/django-kway
Author: Fabio Caccamo
Author-email: fabio.caccamo@gmail.com
License: UNKNOWN
Download-URL: https://github.com/fabiocaccamo/django-kway/archive/0.1.9.tar.gz
Keywords: django,admin,i18n,gettext,trans,alternative,key,modeltranslation,rosetta
Platform: UNKNOWN
Requires: django(>=1.4)
